ramu/__init__.py
ramu/cli.py
ramu/ramu.py
ramu-0.1.0.dist-info/AUTHORS.rst
ramu-0.1.0.dist-info/METADATA
ramu-0.1.0.dist-info/WHEEL
ramu-0.1.0.dist-info/entry_points.txt
ramu-0.1.0.dist-info/top_level.txt
ramu-0.1.0.dist-info/RECORD
